LICENSE
README.md
xpert/__init__.py
xpert/cli_app.py
xpert/config.py
xpert-0.1.1.dist-info/METADATA
xpert-0.1.1.dist-info/WHEEL
xpert-0.1.1.dist-info/entry_points.txt
xpert-0.1.1.dist-info/licenses/LICENSE
xpert-0.1.1.dist-info/RECORD
